mem.v
module mem_control
(
    input clk,
    input [7:0] addr,
    input read_en,

    output reg [7:0] data_out = 0,
    output reg [7:0] output_addr,
    output reg flag = 0
);

reg signed [1:0] i = 0;
reg [7:0] mem [15:0];
reg [7:0] buff [3:0];
reg [3:0] is_valid = 0;
reg [7:0] slct; 

integer j;
integer p;

initial
begin
    mem[0] = 8'd33;
    mem[1] = 14;
    mem[2] = 69;
    mem[3] = 11;
    mem[4] = 54;
    mem[5] = 47;
    mem[6] = 99;
    mem[7] = 96;
    mem[8] = 23;
    mem[9] = 1;
    mem[10] = 78;
    mem[11] = 52;
    mem[12] = 22;
    mem[13] = 13;
    mem[14] = 19;
    mem[15] = 17;
end

always @(posedge clk) 
    if (read_en)
    begin
        p=0;
        for (j=0; j < 4; j = j +1)
            if (is_valid[j] == 0)
                if (p == 0) 
                    begin
                        is_valid[j] <= 1;
                        buff[j] <= addr;
                        p=1;
                    end      
    end

always @(posedge clk)
begin
    p=0;
    flag = 0;
    for (j=0; j < 2; j = j +1)
    begin
        slct = $random%4;
        if (is_valid[slct])
            if (p==0)
                begin
                    data_out <= mem[buff[slct]];
                    p=1;
                    is_valid[slct] <= 0;
                    flag <= 1;
                    output_addr <= buff[slct];
                end    
    end
end


endmodule

test.v
module tb;
    reg clk = 0;
    reg read_en = 0;

    reg [7:0] addr;

    initial 
    begin
        forever #20 clk = ~clk; 
    end

    initial
    begin
        #10
        addr = 8'd2;
        #40
        addr = 8'd11;
        #40
        addr = 8'd1;
        #40
        addr = 8'd13;
        #20
        read_en = 1;
    end

    initial
    begin
        #10
        read_en = 1;
        #20
        read_en = 0;
        #20
        read_en = 1;
        #20
        read_en = 0;
        #20
        read_en = 1;
        #20
        read_en = 0;
        #20
        read_en = 1;
        #20
        read_en = 0;
    end

    initial
    begin
        #500 $finish;
    end

    initial
    begin
        $dumpfile("dump.vcd");
        $dumpvars(0, tb);
    end

    mem_control mem0 (
        .clk(clk),
        .read_en(read_en),
        .addr(addr)
    );

endmodule

dump.vcd
$date
	Mon May 29 02:41:22 2023
$end
$version
	Icarus Verilog
$end
$timescale
	1s
$end
$scope module tb $end
$var reg 8 ! addr [7:0] $end
$var reg 1 " clk $end
$var reg 1 # read_en $end
$scope module mem0 $end
$var wire 8 $ addr [7:0] $end
$var wire 1 % clk $end
$var wire 1 & read_en $end
$var reg 8 ' data_out [7:0] $end
$var reg 1 ( flag $end
$var reg 2 ) i [1:0] $end
$var reg 4 * is_valid [3:0] $end
$var integer 32 + j [31:0] $end
$var reg 8 , output_addr [7:0] $end
$var integer 32 - p [31:0] $end
$var reg 8 . slct [7:0] $end
$upscope $end
$upscope $end
$enddefinitions $end
#0
$dumpvars
bx .
bx -
bx ,
bx +
b0 *
b0 )
0(
b0 '
0&
0%
bx $
0#
0"
bx !
$end
#10
1#
1&
b10 !
b10 $
#20
b1 *
b11111101 .
b100 +
b1 -
1"
1%
#30
0#
0&
#40
0"
0%
#50
1#
1&
b1011 !
b1011 $
#60
b11 *
b11111111 .
b10 +
b0 -
1"
1%
#70
0#
0&
#80
0"
0%
#90
1#
1&
b1 !
b1 $
#100
b1011 ,
1(
b101 *
b110100 '
b1 -
b1 .
b100 +
1"
1%
#110
0#
0&
#120
0"
0%
#130
1#
1&
b1101 !
b1101 $
#140
b111 *
b11111110 .
0(
b10 +
b0 -
1"
1%
#150
0#
0&
#160
0"
0%
#180
b1101 ,
1(
b101 *
b1101 '
b1 -
b1 .
b10 +
1"
1%
#200
0"
0%
#220
b1 ,
b1 *
b1110 '
b1 .
b10 +
1(
b1 -
1"
1%
#240
0"
0%
#260
b10 ,
b0 *
b1000101 '
b0 .
b10 +
1(
b1 -
1"
1%
#280
0"
0%
#300
b11111110 .
b10 +
0(
b0 -
1"
1%
#320
0"
0%
#340
b11111110 .
b10 +
1"
1%
#360
0"
0%
#380
b11111111 .
b10 +
1"
1%
#400
0"
0%
#420
b11 .
b10 +
1"
1%
#440
0"
0%
#460
b11111110 .
b10 +
1"
1%
#480
0"
0%
#500
b0 +
1"
1%
